loc_collector/__init__.py
loc_collector/locator_collector.py
loc_collector-0.1.dist-info/METADATA
loc_collector-0.1.dist-info/WHEEL
loc_collector-0.1.dist-info/top_level.txt
loc_collector-0.1.dist-info/RECORD
