Metadata-Version: 2.1
Name: loc-collector
Version: 0.1
Summary: Locator_collector
Home-page: https://github.com/suri-53/robotretirer
Author: Suriya
Author-email: suriya@nada.com
License: UNKNOWN
Platform: UNKNOWN
Classifier: Framework :: Robot Framework
Classifier: Programming Language :: Python :: 3
Classifier: License :: OSI Approved :: MIT License
Classifier: Operating System :: OS Independent
Requires-Python: >=3.10
